<?xml version="1.0" ?>
<!DOCTYPE DjVuXML>
<DjVuXML>
<HEAD>file://localhost/D:/tmp_3243732/djvu/page0000079.djvu</HEAD>
<BODY>
<OBJECT data="file://localhost/D:/tmp_3243732/djvu/page0000079.djvu" type="image/x.djvu" height="6450" width="4725" usemap="page0000079.djvu" >
<PARAM name="DPI" value="600" />
<PARAM name="GAMMA" value="2.200000" />
  <HIDDENTEXT>
    <PAGECOLUMN>
      <REGION>
        <PARAGRAPH>
          <LINE>
            <WORD coords="1175,411,1461,319">FOR</WORD>
            <WORD coords="1526,411,1948,319">YOUR</WORD>
            <WORD coords="2011,411,2702,319">READING</WORD>
            <WORD coords="2767,411,3545,319">PLEASURE</WORD>
          </LINE>
          <LINE>
            <WORD coords="457,553,660,461">GO</WORD>
            <WORD coords="728,553,1237,461">INSIDE</WORD>
            <WORD coords="1307,551,1607,461">THE</WORD>
            <WORD coords="1676,553,2440,460">GLAMOUR</WORD>
            <WORD coords="2505,551,2829,460">AND</WORD>
            <WORD coords="2897,551,3197,461">THE</WORD>
            <WORD coords="3264,553,4011,461">INTRIGUE</WORD>
            <WORD coords="4080,553,4267,461">OF</WORD>
          </LINE>
        </PARAGRAPH>
      </REGION>
      <REGION>
        <PARAGRAPH>
          <LINE>
            <WORD coords="886,828,2562,644">DOWNTON</WORD>
            <WORD coords="2726,826,3834,644">ABBEY</WORD>
          </LINE>
        </PARAGRAPH>
      </REGION>
      <REGION>
        <PARAGRAPH>
          <LINE>
            <WORD coords="3201,1629,3212,1618">.</WORD>
            <WORD coords="3217,1648,3226,1635">.</WORD>
          </LINE>
        </PARAGRAPH>
      </REGION>
      <REGION>
        <PARAGRAPH>
          <LINE>
            <WORD coords="2241,2171,2260,2141">&apos;Þ:</WORD>
          </LINE>
        </PARAGRAPH>
      </REGION>
      <REGION>
        <PARAGRAPH>
          <LINE>
            <WORD coords="1247,2246,1263,2228">&quot;</WORD>
          </LINE>
          <LINE>
            <WORD coords="1267,2272,1288,2258">.</WORD>
          </LINE>
        </PARAGRAPH>
      </REGION>
      <REGION>
        <PARAGRAPH>
          <LINE>
            <WORD coords="1569,2418,1608,2372">&apos;\</WORD>
            <WORD coords="1664,2412,1666,2405">&quot;</WORD>
          </LINE>
        </PARAGRAPH>
      </REGION>
      <REGION>
        <PARAGRAPH>
          <LINE>
            <WORD coords="1252,2456,1287,2420">..</WORD>
          </LINE>
          <LINE>
            <WORD coords="1256,2484,1336,2456">&apos;.&apos;</WORD>
            <WORD coords="1444,2485,1465,2469">&quot;</WORD>
          </LINE>
          <LINE>
            <WORD coords="1350,2522,1396,2483">&apos;&quot;</WORD>
            <WORD coords="1473,2508,1488,2498">&quot;</WORD>
          </LINE>
          <LINE>
            <WORD coords="1324,2549,1339,2543">-</WORD>
            <WORD coords="1394,2577,1454,2544">......</WORD>
          </LINE>
          <LINE>
            <WORD coords="1308,2597,1366,2562">&quot;&quot;\.:</WORD>
            <WORD coords="1460,2598,1472,2586">,</WORD>
            <WORD coords="1563,2607,1578,2597">..</WORD>
            <WORD coords="1632,2626,1654,2591">&#10; </WORD>
          </LINE>
          <LINE>
            <WORD coords="1406,2642,1421,2602">&#10; </WORD>
            <WORD coords="1563,2645,1594,2609">:0.</WORD>
            <WORD coords="1616,2650,1628,2628">&apos;.</WORD>
          </LINE>
          <LINE>
            <WORD coords="1642,2686,1648,2663">1</WORD>
            <WORD coords="1681,2687,1697,2651">I</WORD>
          </LINE>
        </PARAGRAPH>
      </REGION>
      <REGION>
        <PARAGRAPH>
          <LINE>
            <WORD coords="4056,2721,4062,2714">.</WORD>
            <WORD coords="4078,2733,4122,2705">RY</WORD>
          </LINE>
        </PARAGRAPH>
      </REGION>
      <REGION>
        <PARAGRAPH>
          <LINE>
            <WORD coords="1331,3010,1392,2910">\&lt;</WORD>
            <WORD coords="1539,3010,1718,2949">0(&quot;</WORD>
          </LINE>
          <LINE>
            <WORD coords="1344,3042,1349,3011">\</WORD>
            <WORD coords="1377,3045,1383,3035">.</WORD>
            <WORD coords="1405,3039,1421,3032">-</WORD>
          </LINE>
          <LINE>
            <WORD coords="1350,3106,1358,3074">\</WORD>
          </LINE>
        </PARAGRAPH>
      </REGION>
      <REGION>
        <PARAGRAPH>
          <LINE>
            <WORD coords="2321,2867,2360,2850">-&apos;&quot;</WORD>
          </LINE>
          <LINE>
            <WORD coords="2319,2912,2366,2895">-</WORD>
          </LINE>
        </PARAGRAPH>
      </REGION>
      <REGION>
        <PARAGRAPH>
          <LINE>
            <WORD coords="2940,2882,3064,2853">omen</WORD>
            <WORD coords="3089,2883,3172,2838">like</WORD>
            <WORD coords="3274,2882,3399,2837">don&apos;t</WORD>
            <WORD coords="3418,2882,3472,2839">hi</WORD>
            <WORD coords="3552,2882,3580,2854">a</WORD>
            <WORD coords="3601,2899,3683,2838">life.</WORD>
            <WORD coords="3713,2882,3782,2838">We</WORD>
            <WORD coords="3799,2883,3900,2839">cho,</WORD>
            <WORD coords="3992,2882,4126,2839">lothes</WORD>
          </LINE>
          <LINE>
            <WORD coords="2794,2958,2970,2913">and,a</WORD>
            <WORD coords="3014,2958,3122,2913">calls</WORD>
            <WORD coords="3141,2958,3206,2929">an</WORD>
            <WORD coords="3258,2958,3373,2913">work</WORD>
            <WORD coords="3380,2974,3461,2913">for</WORD>
            <WORD coords="3498,2974,3641,2913">harity</WORD>
            <WORD coords="3661,2957,3690,2929">a</WORD>
            <WORD coords="3729,2958,3761,2913">d</WORD>
            <WORD coords="3778,2958,3835,2914">do</WORD>
            <WORD coords="3872,2958,3924,2913">he</WORD>
            <WORD coords="3972,2957,3993,2928">e</WORD>
            <WORD coords="4025,2958,4073,2929">so</WORD>
          </LINE>
          <LINE>
            <WORD coords="2722,3033,2813,2987">But</WORD>
            <WORD coords="2834,3050,2960,2988">really</WORD>
            <WORD coords="2982,3032,3100,2987">we&apos;re</WORD>
            <WORD coords="3116,3033,3242,2989">stuck</WORD>
            <WORD coords="3264,3032,3313,2989">in</WORD>
            <WORD coords="3333,3032,3362,3003">a</WORD>
            <WORD coords="3381,3050,3575,2989">waiting</WORD>
            <WORD coords="3589,3033,3662,3003">roo</WORD>
            <WORD coords="3763,3032,3851,2987">ntzl</WORD>
            <WORD coords="3867,3032,3929,3004">we</WORD>
            <WORD coords="3947,3032,3990,3003">m</WORD>
          </LINE>
        </PARAGRAPH>
      </REGION>
      <REGION>
        <PARAGRAPH>
          <LINE>
            <WORD coords="721,3164,755,3130">&#10; </WORD>
          </LINE>
        </PARAGRAPH>
      </REGION>
      <REGION>
        <PARAGRAPH>
          <LINE>
            <WORD coords="629,3378,648,3359">l.</WORD>
          </LINE>
        </PARAGRAPH>
      </REGION>
      <REGION>
        <PARAGRAPH>
          <LINE>
            <WORD coords="1202,3293,1219,3202">,</WORD>
          </LINE>
          <LINE>
            <WORD coords="1214,3428,1240,3298">\</WORD>
          </LINE>
        </PARAGRAPH>
      </REGION>
      <REGION>
        <PARAGRAPH>
          <LINE>
            <WORD coords="1929,3376,1963,3364">....</WORD>
          </LINE>
          <LINE>
            <WORD coords="1930,3416,2149,3395">!t&#10;I_b.&#10;from,</WORD>
          </LINE>
          <LINE>
            <WORD coords="1934,3436,2170,3416">&quot;&apos;--br&#10;&quot;ft&quot;&quot;</WORD>
          </LINE>
          <LINE>
            <WORD coords="1932,3457,2181,3437">_b&apos;JN.n...WIoIr:__.....</WORD>
          </LINE>
          <LINE>
            <WORD coords="1933,3479,2172,3457">&quot;&apos;1tr.r&#10;&quot;&apos;IIIIIIdng&amp;nItaøM</WORD>
          </LINE>
        </PARAGRAPH>
      </REGION>
      <REGION>
        <PARAGRAPH>
          <LINE>
            <WORD coords="1462,3335,1479,3311">)</WORD>
          </LINE>
        </PARAGRAPH>
      </REGION>
      <REGION>
        <PARAGRAPH>
          <LINE>
            <WORD coords="1537,3472,1564,3448">.</WORD>
          </LINE>
        </PARAGRAPH>
      </REGION>
      <REGION>
        <PARAGRAPH>
          <LINE>
            <WORD coords="618,3547,652,3519">&quot;</WORD>
          </LINE>
          <LINE>
            <WORD coords="575,3584,680,3555">-.......,</WORD>
            <WORD coords="691,3574,703,3551">,</WORD>
          </LINE>
          <LINE>
            <WORD coords="649,3698,752,3574">&#10;\</WORD>
          </LINE>
        </PARAGRAPH>
      </REGION>
      <REGION>
        <PARAGRAPH>
          <LINE>
            <WORD coords="1296,3547,1328,3512">yo</WORD>
          </LINE>
          <LINE>
            <WORD coords="1265,3602,1280,3575">&apos;&quot;</WORD>
          </LINE>
        </PARAGRAPH>
      </REGION>
      <REGION>
        <PARAGRAPH>
          <LINE>
            <WORD coords="3519,3652,3685,3559">Rpve</WORD>
          </LINE>
          <LINE>
            <WORD coords="3681,3718,3840,3629">flee!</WORD>
          </LINE>
        </PARAGRAPH>
      </REGION>
      <REGION>
        <PARAGRAPH>
          <LINE>
            <WORD coords="2921,3639,2975,3573">lr</WORD>
            <WORD coords="2981,3625,2995,3586">t</WORD>
            <WORD coords="2999,3615,3011,3583">1</WORD>
            <WORD coords="3043,3613,3163,3533">and</WORD>
            <WORD coords="3185,3600,3419,3536">Roman</WORD>
          </LINE>
          <LINE>
            <WORD coords="2773,3692,2919,3605">1tiüa</WORD>
            <WORD coords="2985,3648,3007,3615">&quot;J</WORD>
          </LINE>
          <LINE>
            <WORD coords="2637,3766,2753,3673">&#10;&quot;0</WORD>
          </LINE>
        </PARAGRAPH>
      </REGION>
      <REGION>
        <PARAGRAPH>
          <LINE>
            <WORD coords="1414,3741,1505,3685">&apos;I/&quot;&#10;&apos;</WORD>
            <WORD coords="1531,3729,1669,3688">abo-;;;u&apos;fJ1TIffl</WORD>
            <WORD coords="1677,3724,1718,3703">and</WORD>
            <WORD coords="1725,3726,1825,3699">l/fiiiIIHmþ</WORD>
            <WORD coords="1845,3719,1879,3704">mt,</WORD>
          </LINE>
          <LINE>
            <WORD coords="1439,3766,1451,3738">,</WORD>
            <WORD coords="1458,3769,1538,3741">&apos;&apos;&apos;.vn</WORD>
            <WORD coords="1586,3759,1594,3739">I</WORD>
            <WORD coords="1606,3758,1624,3744">m</WORD>
            <WORD coords="1627,3764,1660,3737">for</WORD>
            <WORD coords="1666,3756,1742,3734">IrrlðM</WORD>
            <WORD coords="1750,3748,1764,3745">-</WORD>
            <WORD coords="1770,3752,1800,3732">iI&apos;s</WORD>
            <WORD coords="1808,3751,1814,3735">r</WORD>
            <WORD coords="1842,3766,1885,3731">gap,</WORD>
          </LINE>
          <LINE>
            <WORD coords="1373,3810,1394,3770">..&quot;</WORD>
            <WORD coords="1503,3806,1617,3767">t&apos;&apos;&apos;f</WORD>
            <WORD coords="1624,3792,1733,3769">aristo.rrary</WORD>
            <WORD coords="1741,3784,1783,3764">and</WORD>
            <WORD coords="1842,3778,1847,3770">&#10; </WORD>
            <WORD coords="1854,3778,1859,3769">,</WORD>
            <WORD coords="1869,3779,1873,3776">.</WORD>
          </LINE>
        </PARAGRAPH>
      </REGION>
      <REGION>
        <PARAGRAPH>
          <LINE>
            <WORD coords="777,3842,804,3819">&apos;-</WORD>
          </LINE>
        </PARAGRAPH>
      </REGION>
      <REGION>
        <PARAGRAPH>
          <LINE>
            <WORD coords="1918,3862,1944,3844">..</WORD>
          </LINE>
        </PARAGRAPH>
      </REGION>
      <REGION>
        <PARAGRAPH>
          <LINE>
            <WORD coords="1130,3874,1176,3851">\..</WORD>
          </LINE>
        </PARAGRAPH>
      </REGION>
      <REGION>
        <PARAGRAPH>
          <LINE>
            <WORD coords="3504,3916,3537,3886">&#10; </WORD>
          </LINE>
        </PARAGRAPH>
      </REGION>
      <REGION>
        <PARAGRAPH>
          <LINE>
            <WORD coords="2584,4047,2599,4025">&quot;</WORD>
            <WORD coords="2684,4059,2720,4039">e</WORD>
          </LINE>
          <LINE>
            <WORD coords="2581,4087,2601,4067">....</WORD>
          </LINE>
          <LINE>
            <WORD coords="2466,4125,2493,4109">c</WORD>
            <WORD coords="2566,4127,2593,4109">..</WORD>
            <WORD coords="2654,4121,2699,4113">-</WORD>
          </LINE>
        </PARAGRAPH>
      </REGION>
      <REGION>
        <PARAGRAPH>
          <LINE>
            <WORD coords="3343,4087,3445,4030">&quot;</WORD>
          </LINE>
        </PARAGRAPH>
      </REGION>
      <REGION>
        <PARAGRAPH>
          <LINE>
            <WORD coords="3810,4057,3835,4041">.</WORD>
          </LINE>
        </PARAGRAPH>
      </REGION>
      <REGION>
        <PARAGRAPH>
          <LINE>
            <WORD coords="4038,4067,4068,4027">\</WORD>
          </LINE>
        </PARAGRAPH>
      </REGION>
      <REGION>
        <PARAGRAPH>
          <LINE>
            <WORD coords="2864,4151,2928,4125">.-</WORD>
          </LINE>
        </PARAGRAPH>
      </REGION>
      <REGION>
        <PARAGRAPH>
          <LINE>
            <WORD coords="3167,4135,3197,4091">\.</WORD>
          </LINE>
        </PARAGRAPH>
      </REGION>
      <REGION>
        <PARAGRAPH>
          <LINE>
            <WORD coords="645,4241,1209,4136">Spectacular</WORD>
            <WORD coords="1242,4241,1868,4136">photographs,</WORD>
          </LINE>
          <LINE>
            <WORD coords="326,4375,757,4294">beautiful</WORD>
            <WORD coords="796,4400,1261,4294">drawings,</WORD>
            <WORD coords="1304,4375,1473,4295">and</WORD>
            <WORD coords="1509,4375,1840,4294">insider</WORD>
            <WORD coords="1875,4399,2184,4306">quotes</WORD>
          </LINE>
          <LINE>
            <WORD coords="423,4534,655,4454">from</WORD>
            <WORD coords="690,4533,834,4453">the</WORD>
            <WORD coords="873,4534,1059,4465">cast</WORD>
            <WORD coords="1096,4534,1265,4453">and</WORD>
            <WORD coords="1302,4534,1527,4479">crew</WORD>
            <WORD coords="1568,4534,1837,4453">adorn</WORD>
            <WORD coords="1875,4534,2092,4453">each</WORD>
          </LINE>
          <LINE>
            <WORD coords="413,4716,718,4611">glossy</WORD>
            <WORD coords="754,4716,1005,4637">page.</WORD>
            <WORD coords="1042,4692,1265,4611">Also</WORD>
            <WORD coords="1304,4716,1450,4623">get</WORD>
            <WORD coords="1486,4692,1535,4638">a</WORD>
            <WORD coords="1573,4692,1844,4611">sneak</WORD>
            <WORD coords="1877,4716,2105,4611">peek</WORD>
          </LINE>
          <LINE>
            <WORD coords="602,4850,687,4781">at</WORD>
            <WORD coords="725,4850,897,4781">sets</WORD>
            <WORD coords="938,4850,1108,4770">and</WORD>
            <WORD coords="1142,4874,1331,4770">plot</WORD>
            <WORD coords="1366,4851,1644,4770">twists</WORD>
            <WORD coords="1684,4850,1916,4770">from</WORD>
          </LINE>
          <LINE>
            <WORD coords="450,5009,594,4928">the</WORD>
            <WORD coords="631,5033,1111,4928">upcoming</WORD>
            <WORD coords="1151,5009,1488,4928">Season</WORD>
            <WORD coords="1522,5009,1726,4930">Two</WORD>
            <WORD coords="1765,5007,1854,4928">in</WORD>
            <WORD coords="1891,5009,2061,4927">this</WORD>
          </LINE>
          <LINE>
            <WORD coords="517,5191,1095,5086">magnificent</WORD>
            <WORD coords="1131,5191,1663,5086">companion</WORD>
            <WORD coords="1702,5191,1991,5086">guide.</WORD>
          </LINE>
        </PARAGRAPH>
      </REGION>
      <REGION>
        <PARAGRAPH>
          <LINE>
            <WORD coords="2658,4242,2689,4195">l&apos;</WORD>
          </LINE>
        </PARAGRAPH>
      </REGION>
      <REGION>
        <PARAGRAPH>
          <LINE>
            <WORD coords="3848,4226,3867,4201">&apos;&quot;</WORD>
          </LINE>
          <LINE>
            <WORD coords="3832,4249,3856,4231">111</WORD>
          </LINE>
        </PARAGRAPH>
      </REGION>
      <REGION>
        <PARAGRAPH>
          <LINE>
            <WORD coords="3920,4293,3937,4263">J</WORD>
          </LINE>
        </PARAGRAPH>
      </REGION>
      <REGION>
        <PARAGRAPH>
          <LINE>
            <WORD coords="3824,4521,3870,4439">:.</WORD>
            <WORD coords="3924,4521,3981,4450">&#10; </WORD>
          </LINE>
        </PARAGRAPH>
      </REGION>
      <REGION>
        <PARAGRAPH>
          <LINE>
            <WORD coords="2735,4683,2989,4601">THE</WORD>
            <WORD coords="3055,4685,3533,4603">WORLD</WORD>
            <WORD coords="3609,4687,3771,4604">OF</WORD>
          </LINE>
          <LINE>
            <WORD coords="2446,4869,3382,4729">DOWNTON</WORD>
            <WORD coords="3476,4877,4102,4729">ABBEY</WORD>
          </LINE>
        </PARAGRAPH>
      </REGION>
      <REGION>
        <PARAGRAPH>
          <LINE>
            <WORD coords="3274,4967,3284,4934">!</WORD>
            <WORD coords="3300,4946,3307,4930">I</WORD>
          </LINE>
        </PARAGRAPH>
      </REGION>
      <REGION>
        <PARAGRAPH>
          <LINE>
            <WORD coords="2599,4995,2805,4973">r&quot;OHF.\\OHD</WORD>
            <WORD coords="2823,4997,2862,4976">11\</WORD>
          </LINE>
          <LINE>
            <WORD coords="2493,5056,2675,5007">JULIAN</WORD>
            <WORD coords="2697,5056,2969,5011">FELLOWES</WORD>
          </LINE>
        </PARAGRAPH>
      </REGION>
      <REGION>
        <PARAGRAPH>
          <LINE>
            <WORD coords="440,5428,672,5339">THE</WORD>
            <WORD coords="719,5429,1205,5339">PERFECT</WORD>
            <WORD coords="1252,5429,1760,5339">HOLIDAY</WORD>
            <WORD coords="1808,5430,2072,5337">GIFT</WORD>
          </LINE>
          <LINE>
            <WORD coords="691,5570,912,5480">FOR</WORD>
            <WORD coords="946,5569,1202,5479">ANY</WORD>
            <WORD coords="1245,5570,1543,5480">TRUE</WORD>
            <WORD coords="1590,5569,1821,5480">FAN</WORD>
          </LINE>
        </PARAGRAPH>
      </REGION>
      <REGION>
        <PARAGRAPH>
          <LINE>
            <WORD coords="2735,5306,2777,5284">....</WORD>
          </LINE>
          <LINE>
            <WORD coords="2736,5344,2761,5322">t:\</WORD>
          </LINE>
        </PARAGRAPH>
      </REGION>
      <REGION>
        <PARAGRAPH>
          <LINE>
            <WORD coords="3356,5011,3387,4983">h&apos;</WORD>
          </LINE>
          <LINE>
            <WORD coords="3196,5037,3231,5015">I.</WORD>
            <WORD coords="3282,5024,3287,5015">.</WORD>
            <WORD coords="3334,5025,3341,5017">.</WORD>
          </LINE>
          <LINE>
            <WORD coords="3196,5060,3232,5031">&#10; </WORD>
            <WORD coords="3299,5062,3307,5038">1</WORD>
            <WORD coords="3334,5042,3343,5026">1</WORD>
          </LINE>
          <LINE>
            <WORD coords="3228,5102,3237,5094">,</WORD>
            <WORD coords="3285,5126,3361,5060">&quot;\Þt!</WORD>
            <WORD coords="3371,5076,3387,5038">·</WORD>
          </LINE>
          <LINE>
            <WORD coords="3181,5154,3215,5118">t..</WORD>
            <WORD coords="3236,5126,3245,5118">.</WORD>
            <WORD coords="3271,5148,3277,5146">-</WORD>
            <WORD coords="3305,5138,3313,5130">.</WORD>
          </LINE>
          <LINE>
            <WORD coords="3104,5224,3149,5208">I.</WORD>
            <WORD coords="3228,5280,3269,5188">&#10;II</WORD>
          </LINE>
          <LINE>
            <WORD coords="3088,5316,3117,5284">c&apos;</WORD>
          </LINE>
        </PARAGRAPH>
      </REGION>
      <REGION>
        <PARAGRAPH>
          <LINE>
            <WORD coords="3460,5268,3483,5232">p</WORD>
          </LINE>
        </PARAGRAPH>
      </REGION>
      <REGION>
        <PARAGRAPH>
          <LINE>
            <WORD coords="3633,5011,3657,4991">\\</WORD>
            <WORD coords="3671,5011,3693,4992">H</WORD>
            <WORD coords="3703,5014,3819,4992">ITT&quot;&apos;N</WORD>
            <WORD coords="3837,5015,3883,4994">B,\;</WORD>
          </LINE>
          <LINE>
            <WORD coords="3493,5078,3705,5026">JESSICA</WORD>
            <WORD coords="3727,5078,4025,5030">FELLOWES</WORD>
          </LINE>
        </PARAGRAPH>
      </REGION>
      <REGION>
        <PARAGRAPH>
          <LINE>
            <WORD coords="2522,5211,2531,5186">i</WORD>
            <WORD coords="2546,5220,2565,5202">,\&apos;</WORD>
            <WORD coords="2630,5218,2635,5206">I</WORD>
            <WORD coords="2650,5211,2657,5192">I</WORD>
          </LINE>
          <LINE>
            <WORD coords="2565,5252,2587,5222">-&apos;</WORD>
          </LINE>
        </PARAGRAPH>
      </REGION>
      <REGION>
        <PARAGRAPH>
          <LINE>
            <WORD coords="2612,5432,2624,5418">·</WORD>
            <WORD coords="2634,5458,2650,5426">r</WORD>
            <WORD coords="2722,5392,2750,5364">,e</WORD>
            <WORD coords="2816,5474,2860,5418">)&apos;1</WORD>
            <WORD coords="2940,5468,2970,5426">n</WORD>
            <WORD coords="2980,5474,2996,5410">1</WORD>
            <WORD coords="3110,5364,3120,5362">-</WORD>
            <WORD coords="3142,5492,3198,5360">m</WORD>
            <WORD coords="3242,5456,3254,5450">_</WORD>
            <WORD coords="3286,5426,3288,5410">&apos;</WORD>
          </LINE>
          <LINE>
            <WORD coords="2904,5622,3016,5478">Î:</WORD>
            <WORD coords="3052,5622,3262,5498">fnlD</WORD>
            <WORD coords="3288,5496,3300,5488">&quot;</WORD>
          </LINE>
          <LINE>
            <WORD coords="2838,5720,2859,5672">II</WORD>
            <WORD coords="2900,5725,2931,5656">ii</WORD>
            <WORD coords="2944,5726,2971,5658">Ii</WORD>
            <WORD coords="2984,5727,3009,5677">I&apos;</WORD>
            <WORD coords="3089,5716,3093,5683">I</WORD>
            <WORD coords="3145,5746,3197,5628">In</WORD>
            <WORD coords="3232,5698,3235,5690">&apos;</WORD>
          </LINE>
          <LINE>
            <WORD coords="2916,5752,2925,5730">(</WORD>
            <WORD coords="2956,5775,3013,5730">I&apos;t</WORD>
            <WORD coords="3039,5768,3072,5761">_</WORD>
            <WORD coords="3089,5740,3093,5723">I</WORD>
            <WORD coords="3232,5746,3235,5725">I</WORD>
          </LINE>
        </PARAGRAPH>
      </REGION>
      <REGION>
        <PARAGRAPH>
          <LINE>
            <WORD coords="3790,5411,3829,5371">A</WORD>
            <WORD coords="3846,5412,4222,5371">COMPANION</WORD>
          </LINE>
          <LINE>
            <WORD coords="3768,5471,4017,5430">EDITION</WORD>
            <WORD coords="4038,5471,4119,5430">TO</WORD>
            <WORD coords="4136,5470,4219,5430">TH</WORD>
            <WORD coords="4230,5470,4254,5431">E</WORD>
          </LINE>
        </PARAGRAPH>
      </REGION>
      <REGION>
        <PARAGRAPH>
          <LINE>
            <WORD coords="2520,5590,2525,5580">.</WORD>
            <WORD coords="2547,5586,2559,5528">f</WORD>
          </LINE>
        </PARAGRAPH>
      </REGION>
      <REGION>
        <PARAGRAPH>
          <LINE>
            <WORD coords="3788,5568,3801,5552">·</WORD>
            <WORD coords="3876,5596,3983,5528">TE</WORD>
            <WORD coords="4002,5620,4319,5528">RJ&apos;IECE</WORD>
          </LINE>
        </PARAGRAPH>
      </REGION>
      <REGION>
        <PARAGRAPH>
          <LINE>
            <WORD coords="2678,5712,2688,5648">I</WORD>
            <WORD coords="2692,5663,2699,5650">&apos;</WORD>
            <WORD coords="2714,5666,2719,5644">I</WORD>
          </LINE>
          <LINE>
            <WORD coords="2690,5712,2717,5666">II</WORD>
          </LINE>
        </PARAGRAPH>
      </REGION>
      <REGION>
        <PARAGRAPH>
          <LINE>
            <WORD coords="3735,5701,4174,5659">PRESENTATION</WORD>
            <WORD coords="4196,5701,4286,5660">ON</WORD>
          </LINE>
          <LINE>
            <WORD coords="3957,5846,4153,5738">Q)PBS</WORD>
          </LINE>
        </PARAGRAPH>
      </REGION>
      <REGION>
        <PARAGRAPH>
          <LINE>
            <WORD coords="755,5787,843,5734">Go</WORD>
            <WORD coords="863,5786,1068,5734">behind</WORD>
            <WORD coords="1087,5786,1177,5734">the</WORD>
            <WORD coords="1199,5787,1348,5734">book</WORD>
            <WORD coords="1367,5786,1472,5734">and</WORD>
            <WORD coords="1496,5786,1587,5750">see</WORD>
            <WORD coords="1608,5787,1760,5750">more</WORD>
          </LINE>
          <LINE>
            <WORD coords="655,5881,876,5813">spreads</WORD>
            <WORD coords="898,5865,972,5830">on</WORD>
            <WORD coords="991,5881,1860,5813">facebook.com/stmartinspress</WORD>
          </LINE>
          <LINE>
            <WORD coords="916,6017,1003,5943">&#10; </WORD>
            <WORD coords="1021,6010,1099,5952">St.</WORD>
            <WORD coords="1135,6009,1403,5954">Martin&apos;s</WORD>
            <WORD coords="1439,6009,1600,5954">Press</WORD>
          </LINE>
        </PARAGRAPH>
      </REGION>
      <REGION>
        <PARAGRAPH>
          <LINE>
            <WORD coords="2693,5875,2767,5794">F</WORD>
          </LINE>
          <LINE>
            <WORD coords="2771,5888,2803,5855">e</WORD>
            <WORD coords="2825,5937,2927,5860">See</WORD>
            <WORD coords="3653,5947,3773,5849">ke&lt;1</WORD>
          </LINE>
          <LINE>
            <WORD coords="2929,5968,3041,5909">refs</WORD>
            <WORD coords="3063,5990,3183,5929">and</WORD>
            <WORD coords="3207,6016,3443,5939">History</WORD>
            <WORD coords="3473,5986,3585,5908">Unl</WORD>
            <WORD coords="3591,5967,3657,5916">oc</WORD>
          </LINE>
        </PARAGRAPH>
      </REGION>
    </PAGECOLUMN>
  </HIDDENTEXT>
</OBJECT>
<MAP name="page0000079.djvu"/>
</BODY>
</DjVuXML>
